{
    "code": [],
    "collection": [],
    "description": [],
    "distributorPartNumber": [],
    "eagleBoard": [],
    "eagleSchem": [],
    "footprintEagle": [],
    "footprintEagleDetails": [],
    "footprintKicad": [],
    "footprintKicadDetails": [
        {
            "attributeType": "smd",
            "description": "https://www.bourns.com/docs/Product-Datasheets/mfsm.pdf",
            "name": "Fuse_Bourns_MF-SM_9.5x6.71mm",
            "pins": {
                "shape": "rect",
                "type": "smd"
            },
            "tags": "bourns ptc resettable fuse polyfuse MF-SM MF-SMHT",
            "threeDModel": "${KICAD6_3DMODEL_DIR}/Fuse.3dshapes/Fuse_Bourns_MF-SM_9.5x6.71mm.wrl"
        }
    ],
    "gitName": [],
    "gitRepo": [],
    "hexID": [
        "FZKFUFUBOURNSMFSM95X671"
    ],
    "kicadBoard": [],
    "kicadSchem": [],
    "manufacturerPartNumber": [],
    "matchSpecial": [],
    "name": [
        "Fuse : Fuse_Bourns_MF-SM_9.5x6.71mm"
    ],
    "oompColor": [
        "kicad-footprints"
    ],
    "oompDesc": [
        "Fuse"
    ],
    "oompID": [
        "FOOTPRINT-kicad-kicad-footprints-Fuse-Fuse_Bourns_MF-SM_9.5x6.71mm"
    ],
    "oompIndex": [
        "Fuse_Bourns_MF-SM_9.5x6.71mm"
    ],
    "oompInstances": [],
    "oompParts": [],
    "oompSize": [
        "kicad"
    ],
    "oompType": [
        "FOOTPRINT"
    ],
    "oplPartNumber": [],
    "rawParts": [],
    "symbolEagle": [],
    "symbolEagleDetails": [],
    "symbolKicad": [],
    "symbolKicadDetails": []
}