{
    "code": [],
    "collection": [],
    "description": [],
    "distributorPartNumber": [],
    "eagleBoard": [],
    "eagleSchem": [],
    "footprintEagle": [],
    "footprintEagleDetails": [],
    "footprintKicad": [],
    "footprintKicadDetails": [
        {
            "attributeType": "through_hole",
            "description": "Through hole straight socket strip, 1x11, 1.00mm pitch, single row (https://gct.co/files/drawings/bc065.pdf), script generated",
            "name": "PinSocket_1x11_P1.00mm_Vertical",
            "pins": {
                "shape": "rect",
                "type": "thru_hole"
            },
            "tags": "Through hole socket strip THT 1x11 1.00mm single row",
            "threeDModel": "${KICAD6_3DMODEL_DIR}/Connector_PinSocket_1.00mm.3dshapes/PinSocket_1x11_P1.00mm_Vertical.wrl"
        }
    ],
    "gitName": [],
    "gitRepo": [],
    "hexID": [
        "FZKCNPINSO1PINSO1X11P1VERTICAL"
    ],
    "kicadBoard": [],
    "kicadSchem": [],
    "manufacturerPartNumber": [],
    "name": [
        "Connector_PinSocket_1.00mm : PinSocket_1x11_P1.00mm_Vertical"
    ],
    "oompColor": [
        "kicad-footprints"
    ],
    "oompDesc": [
        "Connector_PinSocket_1.00mm"
    ],
    "oompID": [
        "FOOTPRINT-kicad-kicad-footprints-Connector_PinSocket_1.00mm-PinSocket_1x11_P1.00mm_Vertical"
    ],
    "oompIndex": [
        "PinSocket_1x11_P1.00mm_Vertical"
    ],
    "oompInstances": [],
    "oompParts": [],
    "oompSize": [
        "kicad"
    ],
    "oompType": [
        "FOOTPRINT"
    ],
    "oplPartNumber": [],
    "rawParts": [],
    "symbolEagle": [],
    "symbolEagleDetails": [],
    "symbolKicad": [],
    "symbolKicadDetails": []
}