{
    "code": [],
    "collection": [],
    "description": [],
    "distributorPartNumber": [],
    "eagleBoard": [],
    "eagleSchem": [],
    "footprintEagle": [],
    "footprintEagleDetails": [],
    "footprintKicad": [],
    "footprintKicadDetails": [],
    "gitName": [],
    "gitRepo": [],
    "hexID": [
        "SZKOCSSG532CCN"
    ],
    "kicadBoard": [],
    "kicadSchem": [],
    "manufacturerPartNumber": [],
    "matchSpecial": [],
    "name": [
        "Oscillator : SG-5032CCN"
    ],
    "oompColor": [
        "kicad-symbols"
    ],
    "oompDesc": [
        "Oscillator"
    ],
    "oompID": [
        "SYMBOL-kicad-kicad-symbols-Oscillator-SG-5032CCN"
    ],
    "oompIndex": [
        "SG-5032CCN"
    ],
    "oompInstances": [],
    "oompParts": [],
    "oompSize": [
        "kicad"
    ],
    "oompType": [
        "SYMBOL"
    ],
    "oplPartNumber": [],
    "rawParts": [],
    "symbolEagle": [],
    "symbolEagleDetails": [],
    "symbolKicad": [],
    "symbolKicadDetails": [
        [
            {
                "kicadSymbolDatasheet": "https://support.epson.biz/td/api/doc_check.php?dl=brief_SG5032CCN&lang=en",
                "kicadSymbolExtends": "SG-8002LB",
                "kicadSymbolFootprint": "Oscillator:Oscillator_SMD_SeikoEpson_SG8002LB-4Pin_5.0x3.2mm",
                "kicadSymbolReference": "X",
                "kicadSymbolValue": "SG-5032CCN",
                "kicadSymbolki_description": "CMOS Clock Oscillator 2.5 to 50 MHz",
                "kicadSymbolki_fp_filters": "Oscillator*SMD*SeikoEpson*SG8002LB*5.0x3.2mm*",
                "kicadSymbolki_keywords": "Crystal Clock Oscillator"
            }
        ]
    ]
}