{
    "code": [],
    "collection": [],
    "description": [],
    "distributorPartNumber": [],
    "eagleBoard": [],
    "eagleSchem": [],
    "footprintEagle": [],
    "footprintEagleDetails": [],
    "footprintKicad": [],
    "footprintKicadDetails": [],
    "gitName": [],
    "gitRepo": [],
    "hexID": [
        "FZEPHOTOELEMENTSD11XX"
    ],
    "kicadBoard": [],
    "kicadSchem": [],
    "manufacturerPartNumber": [],
    "matchSpecial": [],
    "name": [
        "photo-elements : D11XX"
    ],
    "oompColor": [
        "eagle-default"
    ],
    "oompDesc": [
        "photo-elements"
    ],
    "oompID": [
        "FOOTPRINT-eagle-eagle-default-photo-elements-D11XX"
    ],
    "oompIndex": [
        "D11XX"
    ],
    "oompInstances": [],
    "oompParts": [],
    "oompSize": [
        "eagle"
    ],
    "oompType": [
        "FOOTPRINT"
    ],
    "oplPartNumber": [],
    "rawParts": [],
    "symbolEagle": [],
    "symbolEagleDetails": [],
    "symbolKicad": [],
    "symbolKicadDetails": []
}