{
    "code": [],
    "collection": [],
    "description": [],
    "distributorPartNumber": [],
    "eagleBoard": [],
    "eagleSchem": [],
    "footprintKicad": [],
    "footprintKicadDetails": [
        {
            "attributeType": "through_hole",
            "description": "Generic Phoenix Contact connector footprint for: MSTBVA_2,5/6-G; number of pins: 06; pin pitch: 5.00mm; Vertical || order number: 1755558 12A || order number: 1924237 16A (HC)",
            "name": "PhoenixContact_MSTBVA_2,5_6-G_1x06_P5.00mm_Vertical",
            "pins": {
                "shape": "roundrect",
                "type": "thru_hole"
            },
            "tags": "phoenix_contact connector MSTBVA_01x06_G_5.00mm",
            "threeDModel": "${KICAD6_3DMODEL_DIR}/Connector_Phoenix_MSTB.3dshapes/PhoenixContact_MSTBVA_2,5_6-G_1x06_P5.00mm_Vertical.wrl"
        }
    ],
    "gitName": [],
    "gitRepo": [],
    "hexID": [
        "FZKCNPHOENIXMSTBPHOENIXCONTACTMSTBVA256G1X6P5VERTICAL"
    ],
    "kicadBoard": [],
    "kicadSchem": [],
    "manufacturerPartNumber": [],
    "name": [
        "Connector_Phoenix_MSTB : PhoenixContact_MSTBVA_2,5_6-G_1x06_P5.00mm_Vertical"
    ],
    "oompColor": [
        "kicad-footprints"
    ],
    "oompDesc": [
        "Connector_Phoenix_MSTB"
    ],
    "oompID": [
        "FOOTPRINT-kicad-kicad-footprints-Connector_Phoenix_MSTB-PhoenixContact_MSTBVA_2,5_6-G_1x06_P5.00mm_Vertical"
    ],
    "oompIndex": [
        "PhoenixContact_MSTBVA_2,5_6-G_1x06_P5.00mm_Vertical"
    ],
    "oompInstances": [],
    "oompParts": [],
    "oompSize": [
        "kicad"
    ],
    "oompType": [
        "FOOTPRINT"
    ],
    "oplPartNumber": [],
    "rawParts": [],
    "symbolKicad": [],
    "symbolKicadDetails": []
}