{
    "code": [],
    "collection": [],
    "description": [],
    "distributorPartNumber": [],
    "eagleBoard": [],
    "eagleSchem": [],
    "footprintEagle": [],
    "footprintEagleDetails": [],
    "footprintKicad": [],
    "footprintKicadDetails": [],
    "gitName": [],
    "gitRepo": [],
    "hexID": [
        "SZKDEVICELBKRG"
    ],
    "kicadBoard": [],
    "kicadSchem": [],
    "manufacturerPartNumber": [],
    "name": [
        "Device : LED_BKRG"
    ],
    "oompColor": [
        "kicad-symbols"
    ],
    "oompDesc": [
        "Device"
    ],
    "oompFiles": {
        "": [
            "oomlout_OOMP_eda_V2/SYMBOL/kicad/kicad-symbols/Device/LED_BKRG/"
        ],
        "BASE": [
            "oomlout_OOMP_eda_V2/SYMBOL/kicad/kicad-symbols/Device/LED_BKRG/details.csv"
        ],
        "csv": [
            "oomlout_OOMP_eda_V2/SYMBOL/kicad/kicad-symbols/Device/LED_BKRG/details.csv"
        ],
        "details": [
            "oomlout_OOMP_eda_V2/SYMBOL/kicad/kicad-symbols/Device/LED_BKRG/details.py"
        ],
        "image": [
            "oomlout_OOMP_eda_V2/SYMBOL/kicad/kicad-symbols/Device/LED_BKRG/image.png"
        ],
        "imagePng": [
            "oomlout_OOMP_eda_V2/SYMBOL/kicad/kicad-symbols/Device/LED_BKRG/image.png"
        ],
        "jsonBasic": [
            "oomlout_OOMP_eda_V2/SYMBOL/kicad/kicad-symbols/Device/LED_BKRG/basic.json"
        ],
        "jsonFull": [
            "oomlout_OOMP_eda_V2/SYMBOL/kicad/kicad-symbols/Device/LED_BKRG/full.json"
        ],
        "readme": [
            "oomlout_OOMP_eda_V2/SYMBOL/kicad/kicad-symbols/Device/LED_BKRG/README.md"
        ]
    },
    "oompID": [
        "SYMBOL-kicad-kicad-symbols-Device-LED_BKRG"
    ],
    "oompIndex": [
        "LED_BKRG"
    ],
    "oompInstances": [],
    "oompParts": [],
    "oompSize": [
        "kicad"
    ],
    "oompType": [
        "SYMBOL"
    ],
    "oplPartNumber": [],
    "rawParts": [],
    "symbolEagle": [],
    "symbolEagleDetails": [],
    "symbolKicad": [],
    "symbolKicadDetails": [
        [
            {
                "kicadSymbolDatasheet": "~",
                "kicadSymbolExtends": null,
                "kicadSymbolFootprint": "",
                "kicadSymbolReference": "D",
                "kicadSymbolValue": "LED_BKRG",
                "kicadSymbolki_description": "RGB LED, blue/cathode/red/green",
                "kicadSymbolki_fp_filters": "LED* LED_SMD:* LED_THT:*",
                "kicadSymbolki_keywords": "LED RGB diode"
            }
        ]
    ]
}