{
    "code": [],
    "collection": [],
    "description": [],
    "distributorPartNumber": [],
    "eagleBoard": [],
    "eagleSchem": [],
    "footprintEagle": [],
    "footprintEagleDetails": [],
    "footprintKicad": [],
    "footprintKicadDetails": [],
    "gitName": [],
    "gitRepo": [],
    "hexID": [
        "SZKINTERFACEUARTMAX481E"
    ],
    "kicadBoard": [],
    "kicadSchem": [],
    "manufacturerPartNumber": [],
    "name": [
        "Interface_UART : MAX481E"
    ],
    "oompColor": [
        "kicad-symbols"
    ],
    "oompDesc": [
        "Interface_UART"
    ],
    "oompID": [
        "SYMBOL-kicad-kicad-symbols-Interface_UART-MAX481E"
    ],
    "oompIndex": [
        "MAX481E"
    ],
    "oompInstances": [],
    "oompParts": [],
    "oompSize": [
        "kicad"
    ],
    "oompType": [
        "SYMBOL"
    ],
    "oplPartNumber": [],
    "rawParts": [],
    "symbolEagle": [],
    "symbolEagleDetails": [],
    "symbolKicad": [],
    "symbolKicadDetails": [
        [
            {
                "kicadSymbolDatasheet": "https://datasheets.maximintegrated.com/en/ds/MAX1487E-MAX491E.pdf",
                "kicadSymbolExtends": null,
                "kicadSymbolFootprint": "",
                "kicadSymbolReference": "U",
                "kicadSymbolValue": "MAX481E",
                "kicadSymbolki_description": "Half duplex RS-485/RS-422, 2.5 Mbps, \u00b115kV electro-static discharge (ESD) protection, no slew-rate, with low-power shutdown, with receiver/driver enable, 32 receiver drive kapacitity, DIP-8 and SOIC-8",
                "kicadSymbolki_fp_filters": "DIP*W7.62mm* SOIC*3.9x4.9mm*P1.27mm*",
                "kicadSymbolki_keywords": "Half duplex RS-485/RS-422, 2.5 Mbps, \u00b115kV electro-static discharge (ESD) protection, no slew-rate, with low-power shutdown, with receiver/driver enable, 32 receiver drive kapacitity, DIP-8 and SOIC-8"
            }
        ]
    ]
}