{
    "code": [],
    "collection": [],
    "description": [],
    "distributorPartNumber": [],
    "eagleBoard": [],
    "eagleSchem": [],
    "footprintEagle": [],
    "footprintEagleDetails": [],
    "footprintKicad": [],
    "footprintKicadDetails": [],
    "gitName": [],
    "gitRepo": [],
    "hexID": [
        "SZKSENOPTICALSFH39"
    ],
    "kicadBoard": [],
    "kicadSchem": [],
    "manufacturerPartNumber": [],
    "matchSpecial": [],
    "name": [
        "Sensor_Optical : SFH309"
    ],
    "oompColor": [
        "kicad-symbols"
    ],
    "oompDesc": [
        "Sensor_Optical"
    ],
    "oompFiles": {
        "": [
            "oomlout_OOMP_eda_V2/SYMBOL/kicad/kicad-symbols/Sensor_Optical/SFH309/"
        ],
        "BASE": [
            "oomlout_OOMP_eda_V2/SYMBOL/kicad/kicad-symbols/Sensor_Optical/SFH309/details.csv"
        ],
        "csv": [
            "oomlout_OOMP_eda_V2/SYMBOL/kicad/kicad-symbols/Sensor_Optical/SFH309/details.csv"
        ],
        "details": [
            "oomlout_OOMP_eda_V2/SYMBOL/kicad/kicad-symbols/Sensor_Optical/SFH309/details.py"
        ],
        "image": [
            "oomlout_OOMP_eda_V2/SYMBOL/kicad/kicad-symbols/Sensor_Optical/SFH309/image.png"
        ],
        "imagePng": [
            "oomlout_OOMP_eda_V2/SYMBOL/kicad/kicad-symbols/Sensor_Optical/SFH309/image.png"
        ],
        "jsonBasic": [
            "oomlout_OOMP_eda_V2/SYMBOL/kicad/kicad-symbols/Sensor_Optical/SFH309/basic.json"
        ],
        "jsonFull": [
            "oomlout_OOMP_eda_V2/SYMBOL/kicad/kicad-symbols/Sensor_Optical/SFH309/full.json"
        ],
        "readme": [
            "oomlout_OOMP_eda_V2/SYMBOL/kicad/kicad-symbols/Sensor_Optical/SFH309/README.md"
        ]
    },
    "oompID": [
        "SYMBOL-kicad-kicad-symbols-Sensor_Optical-SFH309"
    ],
    "oompIndex": [
        "SFH309"
    ],
    "oompInstances": [],
    "oompParts": [],
    "oompSize": [
        "kicad"
    ],
    "oompType": [
        "SYMBOL"
    ],
    "oplPartNumber": [],
    "rawParts": [],
    "symbolEagle": [],
    "symbolEagleDetails": [],
    "symbolKicad": [],
    "symbolKicadDetails": [
        [
            {
                "kicadSymbolDatasheet": "http://www.osram-os.com/Graphics/XPic2/00101811_0.pdf/SFH%20309,%20SFH%20309%20FA,%20Lead%20(Pb)%20Free%20Product%20-%20RoHS%20Compliant.pdf",
                "kicadSymbolExtends": null,
                "kicadSymbolFootprint": "LED_THT:LED_D3.0mm_Clear",
                "kicadSymbolReference": "Q",
                "kicadSymbolValue": "SFH309",
                "kicadSymbolki_description": "Phototransistor NPN",
                "kicadSymbolki_fp_filters": "LED*3.0mm*Clear*",
                "kicadSymbolki_keywords": "npn phototransistor"
            }
        ]
    ]
}