{
    "code": [],
    "collection": [],
    "description": [],
    "distributorPartNumber": [],
    "eagleBoard": [],
    "eagleSchem": [],
    "footprintEagle": [],
    "footprintEagleDetails": [],
    "footprintKicad": [],
    "footprintKicadDetails": [],
    "gitName": [],
    "gitRepo": [],
    "hexID": [
        "SZKINTERFACEEXPANSIONTCA9555DBT"
    ],
    "kicadBoard": [],
    "kicadSchem": [],
    "manufacturerPartNumber": [],
    "matchSpecial": [],
    "name": [
        "Interface_Expansion : TCA9555DBT"
    ],
    "oompColor": [
        "kicad-symbols"
    ],
    "oompDesc": [
        "Interface_Expansion"
    ],
    "oompID": [
        "SYMBOL-kicad-kicad-symbols-Interface_Expansion-TCA9555DBT"
    ],
    "oompIndex": [
        "TCA9555DBT"
    ],
    "oompInstances": [],
    "oompParts": [],
    "oompSize": [
        "kicad"
    ],
    "oompType": [
        "SYMBOL"
    ],
    "oplPartNumber": [],
    "rawParts": [],
    "symbolEagle": [],
    "symbolEagleDetails": [],
    "symbolKicad": [],
    "symbolKicadDetails": [
        [
            {
                "kicadSymbolDatasheet": "http://www.ti.com/lit/ds/symlink/tca9555.pdf",
                "kicadSymbolExtends": "TCA9535DBR",
                "kicadSymbolFootprint": "Package_SO:SSOP-24_5.3x8.2mm_P0.65mm",
                "kicadSymbolReference": "U",
                "kicadSymbolValue": "TCA9555DBT",
                "kicadSymbolki_description": "16-bit I/O expander, I2C and SMBus interface, interrupts, w/ pull-ups, SSOP-24",
                "kicadSymbolki_fp_filters": "SSOP*5.3x8.2mm*P0.65mm*",
                "kicadSymbolki_keywords": "ti parallel port"
            }
        ]
    ]
}