{
    "code": [],
    "collection": [],
    "description": [],
    "distributorPartNumber": [],
    "eagleBoard": [],
    "eagleSchem": [],
    "footprintKicad": [],
    "footprintKicadDetails": [],
    "gitName": [],
    "gitRepo": [],
    "hexID": [
        "SZKMECHANICALHPAD2PIN"
    ],
    "kicadBoard": [],
    "kicadSchem": [],
    "manufacturerPartNumber": [],
    "name": [
        "Mechanical : Heatsink_Pad_2Pin"
    ],
    "oompColor": [
        "kicad-symbols"
    ],
    "oompDesc": [
        "Mechanical"
    ],
    "oompFiles": {
        "": [
            "oomlout_OOMP_eda_V2/SYMBOL/kicad/kicad-symbols/Mechanical/Heatsink_Pad_2Pin/"
        ],
        "BASE": [
            "oomlout_OOMP_eda_V2/SYMBOL/kicad/kicad-symbols/Mechanical/Heatsink_Pad_2Pin/details.csv"
        ],
        "csv": [
            "oomlout_OOMP_eda_V2/SYMBOL/kicad/kicad-symbols/Mechanical/Heatsink_Pad_2Pin/details.csv"
        ],
        "details": [
            "oomlout_OOMP_eda_V2/SYMBOL/kicad/kicad-symbols/Mechanical/Heatsink_Pad_2Pin/details.py"
        ],
        "imagePng": [
            "oomlout_OOMP_eda_V2/SYMBOL/kicad/kicad-symbols/Mechanical/Heatsink_Pad_2Pin/image.png"
        ],
        "jsonBasic": [
            "oomlout_OOMP_eda_V2/SYMBOL/kicad/kicad-symbols/Mechanical/Heatsink_Pad_2Pin/basic.json"
        ],
        "readme": [
            "oomlout_OOMP_eda_V2/SYMBOL/kicad/kicad-symbols/Mechanical/Heatsink_Pad_2Pin/README.md"
        ]
    },
    "oompID": [
        "SYMBOL-kicad-kicad-symbols-Mechanical-Heatsink_Pad_2Pin"
    ],
    "oompIndex": [
        "Heatsink_Pad_2Pin"
    ],
    "oompInstances": [],
    "oompParts": [],
    "oompSize": [
        "kicad"
    ],
    "oompType": [
        "SYMBOL"
    ],
    "oplPartNumber": [],
    "rawParts": [],
    "symbolKicad": [],
    "symbolKicadDetails": [
        [
            {
                "kicadSymbolDatasheet": "~",
                "kicadSymbolExtends": null,
                "kicadSymbolFootprint": "",
                "kicadSymbolReference": "HS",
                "kicadSymbolValue": "Heatsink_Pad_2Pin",
                "kicadSymbolki_description": "Heatsink with electrical connection, 2 pin",
                "kicadSymbolki_fp_filters": "Heatsink_*",
                "kicadSymbolki_keywords": "thermal heat temperature"
            }
        ]
    ]
}