{
    "code": [],
    "collection": [],
    "description": [],
    "distributorPartNumber": [],
    "eagleBoard": [],
    "eagleSchem": [],
    "footprintKicad": [],
    "footprintKicadDetails": [
        {
            "attributeType": null,
            "description": "Gauge, Massstab, 10mm, CopperTop, Type 2,",
            "name": "Gauge_10mm_Type2_CopperTop",
            "pins": {},
            "tags": "Gauge Massstab 10mm CopperTop Type 2"
        }
    ],
    "gitName": [],
    "gitRepo": [],
    "hexID": [
        "FZKCSGAUGE1TYPE2CTOP"
    ],
    "kicadBoard": [],
    "kicadSchem": [],
    "manufacturerPartNumber": [],
    "name": [
        "Calibration_Scale : Gauge_10mm_Type2_CopperTop"
    ],
    "oompColor": [
        "kicad-footprints"
    ],
    "oompDesc": [
        "Calibration_Scale"
    ],
    "oompID": [
        "FOOTPRINT-kicad-kicad-footprints-Calibration_Scale-Gauge_10mm_Type2_CopperTop"
    ],
    "oompIndex": [
        "Gauge_10mm_Type2_CopperTop"
    ],
    "oompInstances": [],
    "oompParts": [],
    "oompSize": [
        "kicad"
    ],
    "oompType": [
        "FOOTPRINT"
    ],
    "oplPartNumber": [],
    "rawParts": [],
    "symbolKicad": [],
    "symbolKicadDetails": []
}