{
    "code": [],
    "collection": [],
    "description": [],
    "distributorPartNumber": [],
    "eagleBoard": [],
    "eagleSchem": [],
    "footprintEagle": [],
    "footprintEagleDetails": [],
    "footprintKicad": [],
    "footprintKicadDetails": [],
    "gitName": [],
    "gitRepo": [],
    "hexID": [
        "SZKISOLATORPC3H4A"
    ],
    "kicadBoard": [],
    "kicadSchem": [],
    "manufacturerPartNumber": [],
    "matchSpecial": [],
    "name": [
        "Isolator : PC3H4A"
    ],
    "oompColor": [
        "kicad-symbols"
    ],
    "oompDesc": [
        "Isolator"
    ],
    "oompID": [
        "SYMBOL-kicad-kicad-symbols-Isolator-PC3H4A"
    ],
    "oompIndex": [
        "PC3H4A"
    ],
    "oompInstances": [],
    "oompParts": [],
    "oompSize": [
        "kicad"
    ],
    "oompType": [
        "SYMBOL"
    ],
    "oplPartNumber": [],
    "rawParts": [],
    "symbolEagle": [],
    "symbolEagleDetails": [],
    "symbolKicad": [],
    "symbolKicadDetails": [
        [
            {
                "kicadSymbolDatasheet": "http://www.sharpsma.com/webfm_send/395",
                "kicadSymbolExtends": "PC3H4",
                "kicadSymbolFootprint": "Package_DIP:SMDIP-4_W7.62mm",
                "kicadSymbolReference": "U",
                "kicadSymbolValue": "PC3H4A",
                "kicadSymbolki_description": "AC/DC Optocoupler, Vce 70V, CTR 100-250%, SOP4",
                "kicadSymbolki_fp_filters": "SMDIP*W7.62mm*",
                "kicadSymbolki_keywords": "NPN AC DC Optocoupler"
            }
        ]
    ]
}