{
    "code": [],
    "collection": [],
    "description": [],
    "distributorPartNumber": [],
    "eagleBoard": [],
    "eagleSchem": [],
    "footprintKicad": [],
    "footprintKicadDetails": [],
    "gitName": [],
    "gitRepo": [],
    "hexID": [
        "SZKRELAYSOLIDSTATEMOC3163M"
    ],
    "kicadBoard": [],
    "kicadSchem": [],
    "manufacturerPartNumber": [],
    "name": [
        "Relay_SolidState : MOC3163M"
    ],
    "oompColor": [
        "kicad-symbols"
    ],
    "oompDesc": [
        "Relay_SolidState"
    ],
    "oompFiles": {
        "": [
            "oomlout_OOMP_eda_V2/SYMBOL/kicad/kicad-symbols/Relay_SolidState/MOC3163M/"
        ],
        "BASE": [
            "oomlout_OOMP_eda_V2/SYMBOL/kicad/kicad-symbols/Relay_SolidState/MOC3163M/details.csv"
        ],
        "csv": [
            "oomlout_OOMP_eda_V2/SYMBOL/kicad/kicad-symbols/Relay_SolidState/MOC3163M/details.csv"
        ],
        "details": [
            "oomlout_OOMP_eda_V2/SYMBOL/kicad/kicad-symbols/Relay_SolidState/MOC3163M/details.py"
        ],
        "imagePng": [
            "oomlout_OOMP_eda_V2/SYMBOL/kicad/kicad-symbols/Relay_SolidState/MOC3163M/image.png"
        ],
        "jsonBasic": [
            "oomlout_OOMP_eda_V2/SYMBOL/kicad/kicad-symbols/Relay_SolidState/MOC3163M/basic.json"
        ],
        "jsonFull": [
            "oomlout_OOMP_eda_V2/SYMBOL/kicad/kicad-symbols/Relay_SolidState/MOC3163M/full.json"
        ],
        "readme": [
            "oomlout_OOMP_eda_V2/SYMBOL/kicad/kicad-symbols/Relay_SolidState/MOC3163M/README.md"
        ]
    },
    "oompID": [
        "SYMBOL-kicad-kicad-symbols-Relay_SolidState-MOC3163M"
    ],
    "oompIndex": [
        "MOC3163M"
    ],
    "oompInstances": [],
    "oompParts": [],
    "oompSize": [
        "kicad"
    ],
    "oompType": [
        "SYMBOL"
    ],
    "oplPartNumber": [],
    "rawParts": [],
    "symbolKicad": [],
    "symbolKicadDetails": [
        [
            {
                "kicadSymbolDatasheet": "https://www.onsemi.com/pub/Collateral/MOC3163M-D.pdf",
                "kicadSymbolExtends": "MOC3031M",
                "kicadSymbolFootprint": "",
                "kicadSymbolReference": "U",
                "kicadSymbolValue": "MOC3163M",
                "kicadSymbolki_description": "Zero Cross Opto-Triac, Vdrm 600V, Ift 5mA, dv/dt 1000, DIP6",
                "kicadSymbolki_fp_filters": "DIP*W7.62mm* SMDIP*W9.53mm* DIP*W10.16mm*",
                "kicadSymbolki_keywords": "Opto-Triac Opto Triac Zero Cross"
            }
        ]
    ]
}