{
    "code": [],
    "collection": [],
    "description": [],
    "distributorPartNumber": [],
    "eagleBoard": [],
    "eagleSchem": [],
    "footprintEagle": [],
    "footprintEagleDetails": [],
    "footprintKicad": [],
    "footprintKicadDetails": [],
    "gitName": [],
    "gitRepo": [],
    "hexID": [
        "SZKSENTEMPERATURESI754A2"
    ],
    "kicadBoard": [],
    "kicadSchem": [],
    "manufacturerPartNumber": [],
    "name": [
        "Sensor_Temperature : Si7054-A20"
    ],
    "oompColor": [
        "kicad-symbols"
    ],
    "oompDesc": [
        "Sensor_Temperature"
    ],
    "oompFiles": {
        "": [
            "oomlout_OOMP_eda_V2/SYMBOL/kicad/kicad-symbols/Sensor_Temperature/Si7054-A20/"
        ],
        "BASE": [
            "oomlout_OOMP_eda_V2/SYMBOL/kicad/kicad-symbols/Sensor_Temperature/Si7054-A20/details.csv"
        ],
        "csv": [
            "oomlout_OOMP_eda_V2/SYMBOL/kicad/kicad-symbols/Sensor_Temperature/Si7054-A20/details.csv"
        ],
        "details": [
            "oomlout_OOMP_eda_V2/SYMBOL/kicad/kicad-symbols/Sensor_Temperature/Si7054-A20/details.py"
        ],
        "image": [
            "oomlout_OOMP_eda_V2/SYMBOL/kicad/kicad-symbols/Sensor_Temperature/Si7054-A20/image.png"
        ],
        "imagePng": [
            "oomlout_OOMP_eda_V2/SYMBOL/kicad/kicad-symbols/Sensor_Temperature/Si7054-A20/image.png"
        ],
        "jsonBasic": [
            "oomlout_OOMP_eda_V2/SYMBOL/kicad/kicad-symbols/Sensor_Temperature/Si7054-A20/basic.json"
        ],
        "jsonFull": [
            "oomlout_OOMP_eda_V2/SYMBOL/kicad/kicad-symbols/Sensor_Temperature/Si7054-A20/full.json"
        ],
        "readme": [
            "oomlout_OOMP_eda_V2/SYMBOL/kicad/kicad-symbols/Sensor_Temperature/Si7054-A20/README.md"
        ]
    },
    "oompID": [
        "SYMBOL-kicad-kicad-symbols-Sensor_Temperature-Si7054-A20"
    ],
    "oompIndex": [
        "Si7054-A20"
    ],
    "oompInstances": [],
    "oompParts": [],
    "oompSize": [
        "kicad"
    ],
    "oompType": [
        "SYMBOL"
    ],
    "oplPartNumber": [],
    "rawParts": [],
    "symbolEagle": [],
    "symbolEagleDetails": [],
    "symbolKicad": [],
    "symbolKicadDetails": [
        [
            {
                "kicadSymbolDatasheet": "https://www.silabs.com/documents/public/data-sheets/Si7050-1-3-4-5-A20.pdf",
                "kicadSymbolExtends": "Si7050-A20",
                "kicadSymbolFootprint": "Package_DFN_QFN:DFN-6-1EP_3x3mm_P1mm_EP1.65x2.55mm",
                "kicadSymbolReference": "U",
                "kicadSymbolValue": "Si7054-A20",
                "kicadSymbolki_description": "I2C Temperature Sensor, \u00b10.4\u00baC, DFN-6",
                "kicadSymbolki_fp_filters": "DFN*1EP*3x3mm*P1mm*",
                "kicadSymbolki_keywords": "I2C Temperature Sensor"
            }
        ]
    ]
}