{
    "code": [],
    "collection": [],
    "description": [],
    "distributorPartNumber": [],
    "eagleBoard": [],
    "eagleSchem": [],
    "footprintEagle": [],
    "footprintEagleDetails": [],
    "footprintKicad": [],
    "footprintKicadDetails": [],
    "gitName": [],
    "gitRepo": [],
    "hexID": [
        "FZECONSUBDM9V"
    ],
    "kicadBoard": [],
    "kicadSchem": [],
    "manufacturerPartNumber": [],
    "matchSpecial": [],
    "name": [
        "con-subd : M09V"
    ],
    "oompColor": [
        "eagle-default"
    ],
    "oompDesc": [
        "con-subd"
    ],
    "oompFiles": {
        "": [
            "oomlout_OOMP_eda_V2/FOOTPRINT/eagle/eagle-default/con-subd/M09V/"
        ],
        "BASE": [
            "oomlout_OOMP_eda_V2/FOOTPRINT/eagle/eagle-default/con-subd/M09V/details.csv"
        ],
        "csv": [
            "oomlout_OOMP_eda_V2/FOOTPRINT/eagle/eagle-default/con-subd/M09V/details.csv"
        ],
        "details": [
            "oomlout_OOMP_eda_V2/FOOTPRINT/eagle/eagle-default/con-subd/M09V/details.py"
        ],
        "jsonBasic": [
            "oomlout_OOMP_eda_V2/FOOTPRINT/eagle/eagle-default/con-subd/M09V/basic.json"
        ]
    },
    "oompID": [
        "FOOTPRINT-eagle-eagle-default-con-subd-M09V"
    ],
    "oompIndex": [
        "M09V"
    ],
    "oompInstances": [],
    "oompParts": [],
    "oompSize": [
        "eagle"
    ],
    "oompType": [
        "FOOTPRINT"
    ],
    "oplPartNumber": [],
    "rawParts": [],
    "symbolEagle": [],
    "symbolEagleDetails": [],
    "symbolKicad": [],
    "symbolKicadDetails": []
}