{
    "code": [],
    "collection": [],
    "description": [],
    "distributorPartNumber": [],
    "eagleBoard": [],
    "eagleSchem": [],
    "footprintKicad": [],
    "footprintKicadDetails": [],
    "gitName": [],
    "gitRepo": [],
    "hexID": [
        "SZKSENCURRENTCSLW6B2M"
    ],
    "kicadBoard": [],
    "kicadSchem": [],
    "manufacturerPartNumber": [],
    "name": [
        "Sensor_Current : CSLW6B200M"
    ],
    "oompColor": [
        "kicad-symbols"
    ],
    "oompDesc": [
        "Sensor_Current"
    ],
    "oompFiles": {
        "": [
            "oomlout_OOMP_eda_V2/SYMBOL/kicad/kicad-symbols/Sensor_Current/CSLW6B200M/"
        ],
        "BASE": [
            "oomlout_OOMP_eda_V2/SYMBOL/kicad/kicad-symbols/Sensor_Current/CSLW6B200M/details.csv"
        ],
        "csv": [
            "oomlout_OOMP_eda_V2/SYMBOL/kicad/kicad-symbols/Sensor_Current/CSLW6B200M/details.csv"
        ],
        "details": [
            "oomlout_OOMP_eda_V2/SYMBOL/kicad/kicad-symbols/Sensor_Current/CSLW6B200M/details.py"
        ],
        "imagePng": [
            "oomlout_OOMP_eda_V2/SYMBOL/kicad/kicad-symbols/Sensor_Current/CSLW6B200M/image.png"
        ],
        "jsonBasic": [
            "oomlout_OOMP_eda_V2/SYMBOL/kicad/kicad-symbols/Sensor_Current/CSLW6B200M/basic.json"
        ],
        "readme": [
            "oomlout_OOMP_eda_V2/SYMBOL/kicad/kicad-symbols/Sensor_Current/CSLW6B200M/README.md"
        ]
    },
    "oompID": [
        "SYMBOL-kicad-kicad-symbols-Sensor_Current-CSLW6B200M"
    ],
    "oompIndex": [
        "CSLW6B200M"
    ],
    "oompInstances": [],
    "oompParts": [],
    "oompSize": [
        "kicad"
    ],
    "oompType": [
        "SYMBOL"
    ],
    "oplPartNumber": [],
    "rawParts": [],
    "symbolKicad": [],
    "symbolKicadDetails": [
        [
            {
                "kicadSymbolDatasheet": "https://sensing.honeywell.com/honeywell-sensing-cslw-series-product-sheet-005861-1-en.pdf",
                "kicadSymbolExtends": "CSLW6B1",
                "kicadSymbolFootprint": "Sensor_Current:Honeywell_CSLW",
                "kicadSymbolReference": "U",
                "kicadSymbolValue": "CSLW6B200M",
                "kicadSymbolki_description": "Miniature Wired Open-Loop Current Sensors, 200mA",
                "kicadSymbolki_fp_filters": "Honeywell*CSLW*",
                "kicadSymbolki_keywords": "hall current sensor"
            }
        ]
    ]
}