{
    "code": [],
    "collection": [],
    "description": [],
    "distributorPartNumber": [],
    "eagleBoard": [],
    "eagleSchem": [],
    "footprintEagle": [],
    "footprintEagleDetails": [],
    "footprintKicad": [],
    "footprintKicadDetails": [],
    "gitName": [],
    "gitRepo": [],
    "hexID": [
        "FZECONAVX91773"
    ],
    "kicadBoard": [],
    "kicadSchem": [],
    "manufacturerPartNumber": [],
    "matchSpecial": [],
    "name": [
        "con-avx : 009177003"
    ],
    "oompColor": [
        "eagle-default"
    ],
    "oompDesc": [
        "con-avx"
    ],
    "oompID": [
        "FOOTPRINT-eagle-eagle-default-con-avx-009177003"
    ],
    "oompIndex": [
        "009177003"
    ],
    "oompInstances": [],
    "oompParts": [],
    "oompSize": [
        "eagle"
    ],
    "oompType": [
        "FOOTPRINT"
    ],
    "oplPartNumber": [],
    "rawParts": [],
    "symbolEagle": [],
    "symbolEagleDetails": [],
    "symbolKicad": [],
    "symbolKicadDetails": []
}