{
    "code": [],
    "collection": [],
    "description": [],
    "distributorPartNumber": [],
    "eagleBoard": [],
    "eagleSchem": [],
    "footprintEagle": [],
    "footprintEagleDetails": [],
    "footprintKicad": [],
    "footprintKicadDetails": [],
    "gitName": [],
    "gitRepo": [],
    "hexID": [
        "SZKTIMERPLLSI5345BD"
    ],
    "kicadBoard": [],
    "kicadSchem": [],
    "manufacturerPartNumber": [],
    "name": [
        "Timer_PLL : Si5345B-D"
    ],
    "oompColor": [
        "kicad-symbols"
    ],
    "oompDesc": [
        "Timer_PLL"
    ],
    "oompID": [
        "SYMBOL-kicad-kicad-symbols-Timer_PLL-Si5345B-D"
    ],
    "oompIndex": [
        "Si5345B-D"
    ],
    "oompInstances": [],
    "oompParts": [],
    "oompSize": [
        "kicad"
    ],
    "oompType": [
        "SYMBOL"
    ],
    "oplPartNumber": [],
    "rawParts": [],
    "symbolEagle": [],
    "symbolEagleDetails": [],
    "symbolKicad": [],
    "symbolKicadDetails": [
        [
            {
                "kicadSymbolDatasheet": "https://www.silabs.com/documents/public/data-sheets/Si5345-44-42-D-DataSheet.pdf",
                "kicadSymbolExtends": "Si5345A-D",
                "kicadSymbolFootprint": "Package_DFN_QFN:QFN-64-1EP_9x9mm_P0.5mm_EP5.2x5.2mm",
                "kicadSymbolReference": "U",
                "kicadSymbolValue": "Si5345B-D",
                "kicadSymbolki_description": "Jitter Attenuator/Clock Multiplier, 10-channel, Fractional, 0.001-350 MHz, QFN-64",
                "kicadSymbolki_fp_filters": "QFN*1EP*9x9mm*P0.5mm*",
                "kicadSymbolki_keywords": "Clock Jitter Attenuator Multiplier"
            }
        ]
    ]
}