{
    "code": [],
    "collection": [],
    "description": [],
    "distributorPartNumber": [],
    "eagleBoard": [],
    "eagleSchem": [],
    "footprintKicad": [],
    "footprintKicadDetails": [],
    "gitName": [],
    "gitRepo": [],
    "hexID": [
        "SZKTRANSISTORBJTBC88W"
    ],
    "kicadBoard": [],
    "kicadSchem": [],
    "manufacturerPartNumber": [],
    "name": [
        "Transistor_BJT : BC808W"
    ],
    "oompColor": [
        "kicad-symbols"
    ],
    "oompDesc": [
        "Transistor_BJT"
    ],
    "oompFiles": {
        "": [
            "oomlout_OOMP_eda_V2/SYMBOL/kicad/kicad-symbols/Transistor_BJT/BC808W/"
        ],
        "BASE": [
            "oomlout_OOMP_eda_V2/SYMBOL/kicad/kicad-symbols/Transistor_BJT/BC808W/details.csv"
        ],
        "csv": [
            "oomlout_OOMP_eda_V2/SYMBOL/kicad/kicad-symbols/Transistor_BJT/BC808W/details.csv"
        ],
        "details": [
            "oomlout_OOMP_eda_V2/SYMBOL/kicad/kicad-symbols/Transistor_BJT/BC808W/details.py"
        ],
        "imagePng": [
            "oomlout_OOMP_eda_V2/SYMBOL/kicad/kicad-symbols/Transistor_BJT/BC808W/image.png"
        ],
        "jsonBasic": [
            "oomlout_OOMP_eda_V2/SYMBOL/kicad/kicad-symbols/Transistor_BJT/BC808W/basic.json"
        ],
        "jsonFull": [
            "oomlout_OOMP_eda_V2/SYMBOL/kicad/kicad-symbols/Transistor_BJT/BC808W/full.json"
        ],
        "readme": [
            "oomlout_OOMP_eda_V2/SYMBOL/kicad/kicad-symbols/Transistor_BJT/BC808W/README.md"
        ]
    },
    "oompID": [
        "SYMBOL-kicad-kicad-symbols-Transistor_BJT-BC808W"
    ],
    "oompIndex": [
        "BC808W"
    ],
    "oompInstances": [],
    "oompParts": [],
    "oompSize": [
        "kicad"
    ],
    "oompType": [
        "SYMBOL"
    ],
    "oplPartNumber": [],
    "rawParts": [],
    "symbolKicad": [],
    "symbolKicadDetails": [
        [
            {
                "kicadSymbolDatasheet": "https://www.onsemi.com/pub/Collateral/BC808-D.pdf",
                "kicadSymbolExtends": "BC807W",
                "kicadSymbolFootprint": "Package_TO_SOT_SMD:SOT-323_SC-70",
                "kicadSymbolReference": "Q",
                "kicadSymbolValue": "BC808W",
                "kicadSymbolki_description": "0.8A Ic, 25V Vce, PNP Transistor, SOT-323",
                "kicadSymbolki_fp_filters": "SOT?323*",
                "kicadSymbolki_keywords": "PNP transistor"
            }
        ]
    ]
}