{
    "code": [],
    "collection": [],
    "description": [],
    "distributorPartNumber": [],
    "eagleBoard": [],
    "eagleSchem": [],
    "footprintKicad": [],
    "footprintKicadDetails": [
        {
            "attributeType": "smd",
            "description": "http://media.digikey.com/pdf/Data%20Sheets/CNC%20Tech%20PDFs/HDMI_A_Female_2000-1-2-41-00-BK_Dwg.pdf",
            "name": "HDMI_A_Female_2000-1-2-41-00-BK",
            "pins": {
                "shape": "rect",
                "type": "smd"
            },
            "tags": null
        }
    ],
    "gitName": [],
    "gitRepo": [],
    "hexID": [
        "FZKICADDIGIKEYKICADLIBRARYDIGIKEYFOOTPRINTSHDMIAFEMALE21241BK"
    ],
    "kicadBoard": [],
    "kicadSchem": [],
    "manufacturerPartNumber": [],
    "name": [
        "digikey-footprints : HDMI_A_Female_2000-1-2-41-00-BK"
    ],
    "oompColor": [
        "digikey-kicad-library"
    ],
    "oompDesc": [
        "digikey-footprints"
    ],
    "oompID": [
        "FOOTPRINT-kicad-digikey-kicad-library-digikey-footprints-HDMI_A_Female_2000-1-2-41-00-BK"
    ],
    "oompIndex": [
        "HDMI_A_Female_2000-1-2-41-00-BK"
    ],
    "oompInstances": [],
    "oompParts": [],
    "oompSize": [
        "kicad"
    ],
    "oompType": [
        "FOOTPRINT"
    ],
    "oplPartNumber": [],
    "rawParts": [],
    "symbolKicad": [],
    "symbolKicadDetails": []
}