{
    "code": [],
    "collection": [],
    "description": [],
    "distributorPartNumber": [],
    "eagleBoard": [],
    "eagleSchem": [],
    "footprintKicad": [],
    "footprintKicadDetails": [],
    "gitName": [],
    "gitRepo": [],
    "hexID": [
        "SZKSWITCHSWDIPX4"
    ],
    "kicadBoard": [],
    "kicadSchem": [],
    "manufacturerPartNumber": [],
    "name": [
        "Switch : SW_DIP_x04"
    ],
    "oompColor": [
        "kicad-symbols"
    ],
    "oompDesc": [
        "Switch"
    ],
    "oompID": [
        "SYMBOL-kicad-kicad-symbols-Switch-SW_DIP_x04"
    ],
    "oompIndex": [
        "SW_DIP_x04"
    ],
    "oompInstances": [],
    "oompParts": [],
    "oompSize": [
        "kicad"
    ],
    "oompType": [
        "SYMBOL"
    ],
    "oplPartNumber": [],
    "rawParts": [],
    "symbolKicad": [],
    "symbolKicadDetails": [
        [
            {
                "kicadSymbolDatasheet": "~",
                "kicadSymbolExtends": null,
                "kicadSymbolFootprint": "",
                "kicadSymbolReference": "SW",
                "kicadSymbolValue": "SW_DIP_x04",
                "kicadSymbolki_description": "4x DIP Switch, Single Pole Single Throw (SPST) switch, small symbol",
                "kicadSymbolki_fp_filters": "SW?DIP?x4*",
                "kicadSymbolki_keywords": "dip switch"
            }
        ]
    ]
}