{
    "code": [],
    "collection": [],
    "description": [],
    "distributorPartNumber": [],
    "eagleBoard": [],
    "eagleSchem": [],
    "footprintEagle": [],
    "footprintEagleDetails": [],
    "footprintKicad": [],
    "footprintKicadDetails": [],
    "gitName": [],
    "gitRepo": [],
    "hexID": [
        "SZKTRANSISTORFETFDC86244"
    ],
    "kicadBoard": [],
    "kicadSchem": [],
    "manufacturerPartNumber": [],
    "matchSpecial": [],
    "name": [
        "Transistor_FET : FDC86244"
    ],
    "oompColor": [
        "kicad-symbols"
    ],
    "oompDesc": [
        "Transistor_FET"
    ],
    "oompID": [
        "SYMBOL-kicad-kicad-symbols-Transistor_FET-FDC86244"
    ],
    "oompIndex": [
        "FDC86244"
    ],
    "oompInstances": [],
    "oompParts": [],
    "oompSize": [
        "kicad"
    ],
    "oompType": [
        "SYMBOL"
    ],
    "oplPartNumber": [],
    "rawParts": [],
    "symbolEagle": [],
    "symbolEagleDetails": [],
    "symbolKicad": [],
    "symbolKicadDetails": [
        [
            {
                "kicadSymbolDatasheet": "https://www.onsemi.com/pub/Collateral/FDC86244-D.pdf",
                "kicadSymbolExtends": "FDC2512",
                "kicadSymbolFootprint": "Package_TO_SOT_SMD:SuperSOT-6",
                "kicadSymbolReference": "Q",
                "kicadSymbolValue": "FDC86244",
                "kicadSymbolki_description": "2.3A Id, 150V Vds, N-Channel MOSFET, 144mOhm Ron, SuperSOT-6",
                "kicadSymbolki_fp_filters": "SuperSOT*",
                "kicadSymbolki_keywords": "N-Channel MOSFET"
            }
        ]
    ]
}