{
    "code": [],
    "collection": [],
    "description": [],
    "distributorPartNumber": [],
    "eagleBoard": [],
    "eagleSchem": [],
    "footprintEagle": [],
    "footprintEagleDetails": [],
    "footprintKicad": [],
    "footprintKicadDetails": [],
    "gitName": [],
    "gitRepo": [],
    "hexID": [
        "SZK74XXIEEE74LS24"
    ],
    "kicadBoard": [],
    "kicadSchem": [],
    "manufacturerPartNumber": [],
    "matchSpecial": [],
    "name": [
        "74xx_IEEE : 74LS240"
    ],
    "oompColor": [
        "kicad-symbols"
    ],
    "oompDesc": [
        "74xx_IEEE"
    ],
    "oompID": [
        "SYMBOL-kicad-kicad-symbols-74xx_IEEE-74LS240"
    ],
    "oompIndex": [
        "74LS240"
    ],
    "oompInstances": [],
    "oompParts": [],
    "oompSize": [
        "kicad"
    ],
    "oompType": [
        "SYMBOL"
    ],
    "oplPartNumber": [],
    "rawParts": [],
    "symbolEagle": [],
    "symbolEagleDetails": [],
    "symbolKicad": [],
    "symbolKicadDetails": [
        [
            {
                "kicadSymbolDatasheet": "http://www.ti.com/lit/ds/symlink/sn74ls240.pdf",
                "kicadSymbolExtends": null,
                "kicadSymbolFootprint": "",
                "kicadSymbolReference": "U",
                "kicadSymbolValue": "74LS240",
                "kicadSymbolki_description": "Octal Buffer and Line Driver With 3-State Output, active-low enables, inverting outputs",
                "kicadSymbolki_keywords": "7400 logic ttl low power schottky"
            }
        ]
    ]
}