{
    "code": [],
    "collection": [],
    "description": [],
    "distributorPartNumber": [],
    "eagleBoard": [],
    "eagleSchem": [],
    "footprintEagle": [],
    "footprintEagleDetails": [],
    "footprintKicad": [],
    "footprintKicadDetails": [],
    "gitName": [],
    "gitRepo": [],
    "hexID": [
        "SZKMCUSTSTM8STM8S27C8"
    ],
    "kicadBoard": [],
    "kicadSchem": [],
    "manufacturerPartNumber": [],
    "name": [
        "MCU_ST_STM8 : STM8S207C8"
    ],
    "oompColor": [
        "kicad-symbols"
    ],
    "oompDesc": [
        "MCU_ST_STM8"
    ],
    "oompID": [
        "SYMBOL-kicad-kicad-symbols-MCU_ST_STM8-STM8S207C8"
    ],
    "oompIndex": [
        "STM8S207C8"
    ],
    "oompInstances": [],
    "oompParts": [],
    "oompSize": [
        "kicad"
    ],
    "oompType": [
        "SYMBOL"
    ],
    "oplPartNumber": [],
    "rawParts": [],
    "symbolEagle": [],
    "symbolEagleDetails": [],
    "symbolKicad": [],
    "symbolKicadDetails": [
        [
            {
                "kicadSymbolDatasheet": "https://www.st.com/resource/en/datasheet/stm8s208cb.pdf",
                "kicadSymbolExtends": "STM8S208CB",
                "kicadSymbolFootprint": "Package_QFP:LQFP-48_7x7mm_P0.5mm",
                "kicadSymbolReference": "U",
                "kicadSymbolValue": "STM8S207C8",
                "kicadSymbolki_description": "24MHz, 64K Flash, 2K EEPROM, 10-bit ADC, 2 UARTs, SPI, I\u00b2C, LQFP-48",
                "kicadSymbolki_fp_filters": "LQFP*7x7mm*P0.5mm*",
                "kicadSymbolki_keywords": "STM8 Microcontroller Performance Line"
            }
        ]
    ]
}