{
    "code": [],
    "collection": [],
    "description": [],
    "distributorPartNumber": [],
    "eagleBoard": [],
    "eagleSchem": [],
    "footprintEagle": [],
    "footprintEagleDetails": [],
    "footprintKicad": [],
    "footprintKicadDetails": [],
    "gitName": [],
    "gitRepo": [],
    "hexID": [
        "FZASFV4R1STE1LF"
    ],
    "kicadBoard": [],
    "kicadSchem": [],
    "manufacturerPartNumber": [],
    "matchSpecial": [],
    "name": [
        "adafruit : SFV4R-1STE1LF"
    ],
    "oompColor": [
        "Adafruit-Eagle-Library"
    ],
    "oompDesc": [
        "adafruit"
    ],
    "oompFiles": {
        "": [
            "oomlout_OOMP_eda_V2/FOOTPRINT/eagle/Adafruit-Eagle-Library/adafruit/SFV4R-1STE1LF/"
        ],
        "BASE": [
            "oomlout_OOMP_eda_V2/FOOTPRINT/eagle/Adafruit-Eagle-Library/adafruit/SFV4R-1STE1LF/details.csv"
        ],
        "csv": [
            "oomlout_OOMP_eda_V2/FOOTPRINT/eagle/Adafruit-Eagle-Library/adafruit/SFV4R-1STE1LF/details.csv"
        ],
        "details": [
            "oomlout_OOMP_eda_V2/FOOTPRINT/eagle/Adafruit-Eagle-Library/adafruit/SFV4R-1STE1LF/details.py"
        ],
        "jsonBasic": [
            "oomlout_OOMP_eda_V2/FOOTPRINT/eagle/Adafruit-Eagle-Library/adafruit/SFV4R-1STE1LF/basic.json"
        ]
    },
    "oompID": [
        "FOOTPRINT-eagle-Adafruit-Eagle-Library-adafruit-SFV4R-1STE1LF"
    ],
    "oompIndex": [
        "SFV4R-1STE1LF"
    ],
    "oompInstances": [],
    "oompParts": [],
    "oompSize": [
        "eagle"
    ],
    "oompType": [
        "FOOTPRINT"
    ],
    "oplPartNumber": [],
    "rawParts": [],
    "symbolEagle": [],
    "symbolEagleDetails": [],
    "symbolKicad": [],
    "symbolKicadDetails": []
}