{
    "code": [],
    "collection": [],
    "description": [],
    "distributorPartNumber": [],
    "eagleBoard": [],
    "eagleSchem": [],
    "footprintEagle": [],
    "footprintEagleDetails": [],
    "footprintKicad": [],
    "footprintKicadDetails": [],
    "gitName": [],
    "gitRepo": [],
    "hexID": [
        "SZKCONRAC212DK"
    ],
    "kicadBoard": [],
    "kicadSchem": [],
    "manufacturerPartNumber": [],
    "name": [
        "Converter_ACDC : RAC20-12DK"
    ],
    "oompColor": [
        "kicad-symbols"
    ],
    "oompDesc": [
        "Converter_ACDC"
    ],
    "oompID": [
        "SYMBOL-kicad-kicad-symbols-Converter_ACDC-RAC20-12DK"
    ],
    "oompIndex": [
        "RAC20-12DK"
    ],
    "oompInstances": [],
    "oompParts": [],
    "oompSize": [
        "kicad"
    ],
    "oompType": [
        "SYMBOL"
    ],
    "oplPartNumber": [],
    "rawParts": [],
    "symbolEagle": [],
    "symbolEagleDetails": [],
    "symbolKicad": [],
    "symbolKicadDetails": [
        [
            {
                "kicadSymbolDatasheet": "https://recom-power.com/pdf/Powerline_AC-DC/RAC20-K.pdf",
                "kicadSymbolExtends": null,
                "kicadSymbolFootprint": "Converter_ACDC:Converter_ACDC_Recom_RAC20-xxDK_THT",
                "kicadSymbolReference": "PS",
                "kicadSymbolValue": "RAC20-12DK",
                "kicadSymbolki_description": "20 Watt Dual Output AC/DC power supply \u00b112V \u00b1833mA",
                "kicadSymbolki_fp_filters": "Converter*ACDC*Recom*RAC20*DK*THT*",
                "kicadSymbolki_keywords": "ac dc power supply"
            }
        ]
    ]
}