{
    "code": [],
    "collection": [],
    "description": [],
    "distributorPartNumber": [],
    "eagleBoard": [],
    "eagleSchem": [],
    "footprintEagle": [],
    "footprintEagleDetails": [],
    "footprintKicad": [],
    "footprintKicadDetails": [],
    "gitName": [],
    "gitRepo": [],
    "hexID": [
        "SZKREGULATORCONTROLLERL4981A"
    ],
    "kicadBoard": [],
    "kicadSchem": [],
    "manufacturerPartNumber": [],
    "matchSpecial": [],
    "name": [
        "Regulator_Controller : L4981A"
    ],
    "oompColor": [
        "kicad-symbols"
    ],
    "oompDesc": [
        "Regulator_Controller"
    ],
    "oompID": [
        "SYMBOL-kicad-kicad-symbols-Regulator_Controller-L4981A"
    ],
    "oompIndex": [
        "L4981A"
    ],
    "oompInstances": [],
    "oompParts": [],
    "oompSize": [
        "kicad"
    ],
    "oompType": [
        "SYMBOL"
    ],
    "oplPartNumber": [],
    "rawParts": [],
    "symbolEagle": [],
    "symbolEagleDetails": [],
    "symbolKicad": [],
    "symbolKicadDetails": [
        [
            {
                "kicadSymbolDatasheet": "http://www.st.com/resource/en/datasheet/l4981.pdf",
                "kicadSymbolExtends": null,
                "kicadSymbolFootprint": "",
                "kicadSymbolReference": "U",
                "kicadSymbolValue": "L4981A",
                "kicadSymbolki_description": "Power Factor Corrector, Fixed Frequency Average Current Mode, DIP-20/SOIC-20",
                "kicadSymbolki_fp_filters": "SOIC*7.5x12.8mm*P1.27mm* DIP*W7.62mm*",
                "kicadSymbolki_keywords": "SMPS pfc controller"
            }
        ]
    ]
}