{
    "code": [],
    "collection": [],
    "description": [],
    "distributorPartNumber": [],
    "eagleBoard": [],
    "eagleSchem": [],
    "footprintEagle": [],
    "footprintEagleDetails": [],
    "footprintKicad": [],
    "footprintKicadDetails": [
        {
            "attributeType": "smd",
            "description": "Texas Instruments, BGA Microstar Junior, 2x2.5mm, 12 bump 4x3 grid, NSMD pad definition (http://www.ti.com/lit/ds/symlink/txb0104.pdf, http://www.ti.com/lit/wp/ssyz015b/ssyz015b.pdf)",
            "name": "Texas_MicroStar_Junior_BGA-12_2.0x2.5mm_Layout4x3_P0.5mm",
            "pins": {
                "shape": "circle",
                "type": "smd"
            },
            "tags": "Texas_Junior_BGA-12",
            "threeDModel": "${KICAD6_3DMODEL_DIR}/Package_BGA.3dshapes/Texas_MicroStar_Junior_BGA-12_2.0x2.5mm_Layout4x3_P0.5mm.wrl"
        }
    ],
    "gitName": [],
    "gitRepo": [],
    "hexID": [
        "FZKBGATEXASMSTARJUNIORBGA122X25LAYOUT4X3P5"
    ],
    "kicadBoard": [],
    "kicadSchem": [],
    "manufacturerPartNumber": [],
    "name": [
        "Package_BGA : Texas_MicroStar_Junior_BGA-12_2.0x2.5mm_Layout4x3_P0.5mm"
    ],
    "oompColor": [
        "kicad-footprints"
    ],
    "oompDesc": [
        "Package_BGA"
    ],
    "oompID": [
        "FOOTPRINT-kicad-kicad-footprints-Package_BGA-Texas_MicroStar_Junior_BGA-12_2.0x2.5mm_Layout4x3_P0.5mm"
    ],
    "oompIndex": [
        "Texas_MicroStar_Junior_BGA-12_2.0x2.5mm_Layout4x3_P0.5mm"
    ],
    "oompInstances": [],
    "oompParts": [],
    "oompSize": [
        "kicad"
    ],
    "oompType": [
        "FOOTPRINT"
    ],
    "oplPartNumber": [],
    "rawParts": [],
    "symbolEagle": [],
    "symbolEagleDetails": [],
    "symbolKicad": [],
    "symbolKicadDetails": []
}