{
    "code": [],
    "collection": [],
    "description": [],
    "distributorPartNumber": [],
    "eagleBoard": [],
    "eagleSchem": [],
    "footprintEagle": [],
    "footprintEagleDetails": [],
    "footprintKicad": [],
    "footprintKicadDetails": [],
    "gitName": [],
    "gitRepo": [],
    "hexID": [
        "SZKTRANSISTORFETIRF748M"
    ],
    "kicadBoard": [],
    "kicadSchem": [],
    "manufacturerPartNumber": [],
    "name": [
        "Transistor_FET : IRF7480M"
    ],
    "oompColor": [
        "kicad-symbols"
    ],
    "oompDesc": [
        "Transistor_FET"
    ],
    "oompFiles": {
        "": [
            "oomlout_OOMP_eda_V2/SYMBOL/kicad/kicad-symbols/Transistor_FET/IRF7480M/"
        ],
        "BASE": [
            "oomlout_OOMP_eda_V2/SYMBOL/kicad/kicad-symbols/Transistor_FET/IRF7480M/details.csv"
        ],
        "csv": [
            "oomlout_OOMP_eda_V2/SYMBOL/kicad/kicad-symbols/Transistor_FET/IRF7480M/details.csv"
        ],
        "details": [
            "oomlout_OOMP_eda_V2/SYMBOL/kicad/kicad-symbols/Transistor_FET/IRF7480M/details.py"
        ],
        "image": [
            "oomlout_OOMP_eda_V2/SYMBOL/kicad/kicad-symbols/Transistor_FET/IRF7480M/image.png"
        ],
        "imagePng": [
            "oomlout_OOMP_eda_V2/SYMBOL/kicad/kicad-symbols/Transistor_FET/IRF7480M/image.png"
        ],
        "jsonBasic": [
            "oomlout_OOMP_eda_V2/SYMBOL/kicad/kicad-symbols/Transistor_FET/IRF7480M/basic.json"
        ],
        "jsonFull": [
            "oomlout_OOMP_eda_V2/SYMBOL/kicad/kicad-symbols/Transistor_FET/IRF7480M/full.json"
        ],
        "readme": [
            "oomlout_OOMP_eda_V2/SYMBOL/kicad/kicad-symbols/Transistor_FET/IRF7480M/README.md"
        ]
    },
    "oompID": [
        "SYMBOL-kicad-kicad-symbols-Transistor_FET-IRF7480M"
    ],
    "oompIndex": [
        "IRF7480M"
    ],
    "oompInstances": [],
    "oompParts": [],
    "oompSize": [
        "kicad"
    ],
    "oompType": [
        "SYMBOL"
    ],
    "oplPartNumber": [],
    "rawParts": [],
    "symbolEagle": [],
    "symbolEagleDetails": [],
    "symbolKicad": [],
    "symbolKicadDetails": [
        [
            {
                "kicadSymbolDatasheet": "https://www.infineon.com/dgdl/Infineon-IRF7480M-DS-v01_02-EN.pdf?fileId=5546d462533600a4015355ff8fa41c30",
                "kicadSymbolExtends": "IRF60DM206",
                "kicadSymbolFootprint": "Package_DirectFET:DirectFET_ME",
                "kicadSymbolReference": "Q",
                "kicadSymbolValue": "IRF7480M",
                "kicadSymbolki_description": "330A Id, 40V Vds, 1.2mOhm Rds, N-Channel MOSFET, DirectFET ME",
                "kicadSymbolki_fp_filters": "DirectFET*ME*",
                "kicadSymbolki_keywords": "N-Channel MOSFET"
            }
        ]
    ]
}